discretefirstorder/__init__.py
discretefirstorder/_dfo_optim.py
discretefirstorder/_discrete_first_order.py
discretefirstorder/_losses.py
discretefirstorder/_version.py
discretefirstorder/tests/__init__.py
discretefirstorder/tests/test_common.py
discretefirstorder/tests/test_dfo_optim.py
discretefirstorder/tests/test_discrete_first_order.py
discretefirstorder/tests/test_losses.py
sklearn_discretefirstorder-0.0.2.dist-info/LICENSE
sklearn_discretefirstorder-0.0.2.dist-info/METADATA
sklearn_discretefirstorder-0.0.2.dist-info/WHEEL
sklearn_discretefirstorder-0.0.2.dist-info/top_level.txt
sklearn_discretefirstorder-0.0.2.dist-info/RECORD
